setup.cfg
setup.py
osimis_cmd_helpers/__init__.py
osimis_cmd_helpers/cmdHelpers.py
osimis_cmd_helpers.egg-info/PKG-INFO
osimis_cmd_helpers.egg-info/SOURCES.txt
osimis_cmd_helpers.egg-info/dependency_links.txt
osimis_cmd_helpers.egg-info/top_level.txt