Metadata-Version: 1.0
Name: osimis-cmd-helpers
Version: 0.1.1
Summary: Helpers to run system commands and get their output.
Home-page: https://bitbucket.org/osimis/python-osimis-cmd-helpers
Author: Alain Mazy
Author-email: am@osimis.io
License: UNKNOWN
Keywords: Helpers,Cmd
Platform: UNKNOWN
